qrng/__init__.py
qrng/_qrng_build.py
semi_classicalqrng_py_bindings-1.1.0.dist-info/LICENSE
semi_classicalqrng_py_bindings-1.1.0.dist-info/METADATA
semi_classicalqrng_py_bindings-1.1.0.dist-info/WHEEL
semi_classicalqrng_py_bindings-1.1.0.dist-info/top_level.txt
semi_classicalqrng_py_bindings-1.1.0.dist-info/RECORD
