Metadata-Version: 2.2
Name: semi_classicalqrng_py_bindings
Version: 1.1.0
Summary: Quantum-inspired Random Number Generator (QRNG) for Python
Author-email: Your Name <you@example.com>
License: MIT
Project-URL: Homepage, https://github.com/yourusername/qrng
Project-URL: Documentation, https://github.com/yourusername/qrng#readme
Project-URL: Repository, https://github.com/yourusername/qrng.git
Project-URL: Issues, https://github.com/yourusername/qrng/issues
Keywords: random,number,generator,quantum,cryptography
Classifier: Development Status :: 5 - Production/Stable
Classifier: Intended Audience :: Developers
Classifier: Intended Audience :: Science/Research
Classifier: License :: OSI Approved :: MIT License
Classifier: Operating System :: OS Independent
Classifier: Programming Language :: Python :: 3
Classifier: Programming Language :: Python :: 3.7
Classifier: Programming Language :: Python :: 3.8
Classifier: Programming Language :: Python :: 3.9
Classifier: Programming Language :: Python :: 3.10
Classifier: Programming Language :: Python :: 3.11
Classifier: Topic :: Scientific/Engineering :: Mathematics
Classifier: Topic :: Security :: Cryptography
Classifier: Topic :: Software Development :: Libraries :: Python Modules
Requires-Python: >=3.7
License-File: LICENSE
Requires-Dist: cffi>=1.15.0
